EasyEventStudies/__init__.py
EasyEventStudies/easy_event_studies.py
EasyEventStudies/test_easy_event_studies.py
EasyEventStudies-1.7.dist-info/LICENSE
EasyEventStudies-1.7.dist-info/METADATA
EasyEventStudies-1.7.dist-info/WHEEL
EasyEventStudies-1.7.dist-info/top_level.txt
EasyEventStudies-1.7.dist-info/RECORD
